[
  {
    "price_transaction": [
      {
        "date": "2026-01-09",
        "type": "sell",
        "price": 112.0,
        "amount_transacted": 500000
      }
    ],
    "title": "Dana Pensiun Bank Pembangunan Daerah Jateng sells shares of PT Asuransi Digital Bersama Tbk",
    "sub_sector": "insurance",
    "transaction_type": "sell",
    "sector": "financials",
    "company_name": "PT Asuransi Digital Bersama Tbk",
    "tags": [
      "investment"
    ],
    "holding_before": 291968700,
    "amount_transaction": 500000,
    "timestamp": "2026-01-12T07:59:34",
    "price": 112.0,
    "purpose_of_transaction": "Investment",
    "holder_name": "Dana Pensiun Bank Pembangunan Daerah Jateng",
    "share_percentage_after": 8.508,
    "share_percentage_transaction": 0.014,
    "body": "Dana Pensiun Bank Pembangunan Daerah Jateng sold 500,000 shares of PT Asuransi Digital Bersama Tbk. This decreases their holdings from 291,968,700 to 291,468,700 shares. The stated purpose of the transaction was investment.",
    "holder_type": "institution",
    "symbol": "YOII.JK",
    "share_percentage_before": 8.522,
    "source": "https://www.idx.co.id/StaticData/NewsAndAnnouncement/ANNOUNCEMENTSTOCK/From_KSEI/LK-12012026-2327-00.pdf-0.pdf",
    "transaction_value": 56000000.0,
    "holding_after": 291468700,
    "type": "sell",
    "amount": 500000,
    "value": 56000000.0,
    "audit_flags": {
      "announcement": {
        "id": "lk-12012026-2327-00.pdf-0",
        "title": "REPORT OF OWNERSHIP OR ANY CHANGES IN SHARE OWNERSHIP OF PUBLIC COMPANIES",
        "url": "https://www.idx.co.id/StaticData/NewsAndAnnouncement/ANNOUNCEMENTSTOCK/From_KSEI/LK-12012026-2327-00.pdf-0.pdf",
        "pdf_url": null,
        "source_type": "idx"
      },
      "document_median_price": 112.0,
      "market_reference": {
        "ref_price": 111.0,
        "ref_type": "close",
        "asof_date": "2026-01-09",
        "n_days": 1,
        "freshness_days": 3
      },
      "total_shares_model": 3426058436.986623,
      "delta_pp_model": -0.015,
      "pp_after_model": 8.507,
      "percent_discrepancy": false,
      "discrepancy_pp": 0.0009999999999994458,
      "needs_review": false,
      "reasons": []
    },
    "percent_discrepancy": false,
    "needs_review": false,
    "market_reference": {
      "ref_price": 111.0,
      "ref_type": "close",
      "asof_date": "2026-01-09",
      "n_days": 1,
      "freshness_days": 3
    },
    "document_median_price": 112.0
  }
]